dfsubset/__init__.py
dfsubset/core.py
dfsubset-0.2.1.dist-info/licenses/LICENSE
dfsubset-0.2.1.dist-info/METADATA
dfsubset-0.2.1.dist-info/WHEEL
dfsubset-0.2.1.dist-info/top_level.txt
dfsubset-0.2.1.dist-info/RECORD
